[{"country":"Kenya","sugar_name":"kabras sugar","products":[{"name":"Kabras Kabras Premium White Sugar - 2kg","price":"KSh 306"},{"name":"Kabras Kabras Premium White Sugar - 1kg","price":"KSh 153"},{"name":"Kabras Sugar 2 Kg X10 Pcs /1Bale","price":"KSh 3,192"},{"name":"Kabras Sugar 1 Kg X20 Pcs /1Bale","price":"KSh 3,255"}]},{"country":"Uganda","sugar_name":"lugazi sugar","products":[{"name":"Lugazi Lugazi Sugar -1kg","price":"UGX 5,000"},{"name":"Lugazi Lugazi Sugar - 5kg","price":"UGX 24,900"},{"name":"Lugazi Sugar 2kg","price":"UGX 10,600"}]},{"country":"Nigeria","sugar_name":"dangote sugar","products":[{"name":"Dangote Sugar 1Kg X1","price":"₦ 950"},{"name":"Dangote Fortified Sugar 500g X 5","price":"₦ 4,500"},{"name":"Checkers Breakfast Exclusive Bundles-Peak Milk, Milo, Checkers Custard & Dangote Sugar","price":"₦ 11,900"},{"name":"Breakfast Exclusive Bundles-Milk, M, Checkers Custard & Dangote Sugar","price":"₦ 12,699"},{"name":"Dangote Sugar - 500g X 5","price":"₦ 5,800"}]}]